<?xml version="1.0" encoding="UTF-8" standalone="yes"?>
<users>
    <user>
        <name>ejemplo</name>
        <email>ejemplo</email>
        <nickname>ejemplo</nickname>
        <password>fd984bad363e9a30021460091726467b65bb1e88c31752d93c68ade87e4946e4</password>
        <contactos>
            <email>ejemploe</email>
            <name>ejemploe</name>
            <nickname>ejemploe</nickname>
        </contactos>
    </user>
    <user>
        <name>ejemploe</name>
        <email>ejemploe</email>
        <nickname>ejemploe</nickname>
        <password>5ba023a42c47c285bebcfbc0df408077b593866d4f8a18903f55a7b2164e163f</password>
        <contactos>
            <email>ejemplo</email>
            <name>ejemplo</name>
            <nickname>ejemplo</nickname>
        </contactos>
    </user>
</users>
